   {
       "name":  "SCREEN_ALL",
       "url": "/api/v1/screen",
       "method": "GET",
       "result": "{{RESULT}}"  
   },
   {
       "name":  "SCREEN_ONE",
       "url": "/api/v1/screen/{id}",
       "method": "GET",
       "result": "{\"pool\": {{RESULT}},\"video\": {{RESULT_V}},\"picture\": {{RESULT_P}} }"  
   },
   {
       "name":  "SCREEN_NEW",
       "url": "/api/v1/screen-new",
       "method": "GET",
       "result": "{\"video\": {{RESULT_V}},\"picture\": {{RESULT_P}} }"  
   },
   {
       "name":  "SCREEN_CREATE",
       "url": "/api/v1/screen",
       "method": "POST",
       "result": "{{RESULT}}"  
   },
   {
       "name":  "SCREEN_UPDATE",
       "url": "/api/v1/screen",
       "method": "PUT",
       "result": "{{RESULT}}"  
   },
   {
       "name":  "SCREEN_DELETE",
       "url": "/api/v1/screen/{ids}",
       "method": "DELETE",
       "result": "{\"result\": {{RESULT}} }"  
   },
